distributions/Binomialdistribution.py
distributions/Gaussiandistribution.py
distributions/Generaldistribution.py
distributions/__init__.py
distributions_2020_0.1-0.1.dist-info/DESCRIPTION.rst
distributions_2020_0.1-0.1.dist-info/METADATA
distributions_2020_0.1-0.1.dist-info/RECORD
distributions_2020_0.1-0.1.dist-info/WHEEL
distributions_2020_0.1-0.1.dist-info/metadata.json
distributions_2020_0.1-0.1.dist-info/top_level.txt
