Metadata-Version: 2.0
Name: distributions-2020-0.1
Version: 0.1
Summary: Gaussian + Binomial distributions
Home-page: UNKNOWN
Author: UNKNOWN
Author-email: UNKNOWN
License: UNKNOWN
Platform: UNKNOWN
